simplex_optimization/__init__.py
simplex_optimization-0.0.1rc1.dist-info/METADATA
simplex_optimization-0.0.1rc1.dist-info/WHEEL
simplex_optimization-0.0.1rc1.dist-info/top_level.txt
simplex_optimization-0.0.1rc1.dist-info/RECORD
