Metadata-Version: 2.4
Name: simplex-optimization
Version: 0.0.1rc1
Summary: Placeholder for novel simplex-optimization gradient descent algorithm.
Author: Ferdinand Koenig
Author-email: ferdinand@koenix.de
Classifier: Programming Language :: Python :: 3
Classifier: Operating System :: OS Independent
Requires-Python: >=3.8,<4
Dynamic: author
Dynamic: author-email
Dynamic: classifier
Dynamic: description
Dynamic: description-content-type
Dynamic: requires-python
Dynamic: summary
